logxstract/__init__.py
logxstract/__main__.py
logxstract/lib.py
logxstract/test.py
logxstract-0.0.1.dist-info/DESCRIPTION.rst
logxstract-0.0.1.dist-info/METADATA
logxstract-0.0.1.dist-info/RECORD
logxstract-0.0.1.dist-info/WHEEL
logxstract-0.0.1.dist-info/entry_points.txt
logxstract-0.0.1.dist-info/metadata.json
logxstract-0.0.1.dist-info/top_level.txt
