Metadata-Version: 2.0
Name: logxstract
Version: 0.0.1
Summary: Library for extracting xml from logs to output file.
Home-page: https://github.com/nuncjo/logxstract
Author: Nuncjo
Author-email: zoreander@gmail.com
License: MIT license
Keywords: xml extractor,xml logs,extract from logs,logs filtering,log
Platform: UNKNOWN
Classifier: Development Status :: 2 - Pre-Alpha
Classifier: Intended Audience :: Developers
Classifier: License :: OSI Approved :: MIT License
Classifier: Natural Language :: English
Classifier: Programming Language :: Python :: 3.6
Classifier: Programming Language :: Python :: 3.5
Classifier: Programming Language :: Python :: 3.4
Classifier: Programming Language :: Python :: 3.2
Classifier: Programming Language :: Python :: 3.1
Classifier: Programming Language :: Python :: 3.0
Classifier: Programming Language :: Python :: 2.7
Requires-Dist: lxml
